binpatch/__init__.py
binpatch/__main__.py
binpatch/diff.py
binpatch/io.py
binpatch/patch.py
binpatch/types.py
binpatch/utils.py
pybinpatch-1.1.2.dist-info/METADATA
pybinpatch-1.1.2.dist-info/WHEEL
pybinpatch-1.1.2.dist-info/RECORD
