Metadata-Version: 2.1
Name: pybinpatch
Version: 1.1.2
Summary: Binary diff and patch lib
Home-page: https://github.com/Merculous/PyBinPatch
Author: Merculous
Author-email: 24739823+Merculous@users.noreply.github.com
Requires-Python: >=3.11,<4.0
Classifier: Programming Language :: Python :: 3
Classifier: Programming Language :: Python :: 3.11
Classifier: Programming Language :: Python :: 3.12
Classifier: Programming Language :: Python :: 3.13
Project-URL: Repository, https://github.com/Merculous/PyBinPatch
